genjutsu/__init__.py
genjutsu-0.1.dev0.dist-info/LICENSE
genjutsu-0.1.dev0.dist-info/METADATA
genjutsu-0.1.dev0.dist-info/WHEEL
genjutsu-0.1.dev0.dist-info/top_level.txt
genjutsu-0.1.dev0.dist-info/RECORD
